{
	"Params": [
		{
			"Param": "DNA_N",
			"Values": [
				{
					"S": "1",
					"Val": {
						"Lower": "50",
						"Upper": "800"
					}
				},
				{
					"S": "2",
					"Val": {
						"Lower": "800",
						"Upper": "1100"
					}
				}
			]
		},
		{
			"Param": "DNA_Q3",
			"Values": [
				{
					"S": "1",
					"Val": {
						"Lower": "40",
						"Upper": "60"
					}
				},
				{
					"S": "2",
					"Val": {
						"Lower": "8000",
						"Upper": "10000"
					}
				}
			]
		},
		{
			"Param": "DNA_Q1",
			"Values": [
				{
					"S": "1",
					"Val": {
						"Lower": "40",
						"Upper": "50"
					}
				},
				{
					"S": "2",
					"Val": {
						"Lower": "8000",
						"Upper": "10000"
					}
				}
			]
		},
		{
			"Param": "DNA_Q2",
			"Values": [
				{
					"S": "1",
					"Val": {
						"Lower": "40",
						"Upper": "50"
					}
				},
				{
					"S": "2",
					"Val": {
						"Lower": "8000",
						"Upper": "10000"
					}
				}
			]
		},
		{
			"Param": "Seq_Q3",
			"Values": [
				{
					"S": "0",
					"Val": {
						"Lower": "0.8",
						"Upper": "99999999999999999999999999"
					}
				}
			]
		},
		{
			"Param": "Seq_Y",
			"Values": [
				{
					"S": "0",
					"Val": {
						"Lower": "0.0001",
						"Upper": "9999999999999999999999999999"
					}
				}
			]
		},
		{
			"Param": "Seq_V",
			"Values": [
				{
					"S": "0",
					"Val": {
						"Lower": "0",
						"Upper": "40"
					}
				}
			]
		},
		{
			"Param": "Seq_LowTE",
			"Values": [
				{
					"S": "0",
					"Val": {
						"Lower": "0",
						"Upper": "40"
					}
				}
			]
		}
	]
}